{"slideshow_credits": null, "snippet": "A mixed reaction from Spanish-Language media for Senator Marco Rubio. The origins of computer matchmaking. Streaming services create original content for children.", "abstract": "A mixed reaction from Spanish-Language media for Senator Marco Rubio. The origins of computer matchmaking. Streaming services create original content for children.", "section_name": "Technology", "print_page": null, "document_type": "blogpost", "byline": {"person": [], "original": "By THE NEW YORK TIMES", "organization": "The New York Times"}, "web_url": "http://bits.blogs.nytimes.com/2013/02/13/timescast-mediatech-spanish-language-media-reacts-to-rubio/", "lead_paragraph": null, "headline": {"main": "TimesCast Media+Tech: Spanish-Language Media Reacts to Rubio", "kicker": "Bits"}, "_id": "511c003500315214fbb8ae57", "word_count": "25", "multimedia": [], "pub_date": "2013-02-13T15:58:32Z", "source": "The New York Times", "news_desk": null, "keywords": [], "blog": [], "subsection_name": null, "type_of_material": "Blog"}