{"slideshow_credits": null, "snippet": "The French food company Danone said it was cutting its sales, profitability and free cash flow goals for 2013 as a result.", "abstract": null, "section_name": "Business Day", "print_page": "", "document_type": "article", "byline": {"person": [], "organization": "REUTERS", "original": "By REUTERS", "contributor": ""}, "web_url": "http://www.nytimes.com/2013/10/17/business/international/slow-recovery-from-recall-hurts-danone.html", "lead_paragraph": "The French food company Danone said it was cutting its sales, profitability and free cash flow goals for 2013 as a result.", "headline": {"main": "Slow Recovery From Recall Hurts Danone", "print_headline": "Slow Recovery From Recall Hurts Danone Shares"}, "_id": "525ec06838f0d86e01ab5ba6", "word_count": "409", "multimedia": [], "pub_date": "2013-10-17T00:00:00Z", "source": "The New York Times", "news_desk": "Business", "keywords": [], "blog": [], "subsection_name": "International Business", "type_of_material": "News"}