{"slideshow_credits": null, "snippet": "Uber, Yik Yak and others have raised more money in less time, driven by money flowing in from hedge funds, strategic investors and more.", "abstract": "Uber, Yik Yak and others have raised more money in less time, driven by money flowing in from hedge funds, strategic investors and more.", "section_name": "Technology", "print_page": null, "document_type": "blogpost", "byline": {"person": [], "original": "By THE NEW YORK TIMES", "organization": "The New York Times"}, "web_url": "http://bits.blogs.nytimes.com/2015/05/11/daily-report-uber-funding-talks-highlight-the-speedy-pace-of-investments/", "lead_paragraph": null, "headline": {"main": "Daily Report: Uber Funding Talks Highlight the Speedy Pace of Investments", "kicker": "Bits"}, "_id": "5550bbc038f0d835cf3efbf7", "word_count": "158", "multimedia": [{"height": 400, "url": "images/2011/11/30/technology/bits-daily-report/bits-daily-report-articleLarge.jpg", "legacy": {"xlarge": "images/2011/11/30/technology/bits-daily-report/bits-daily-report-articleLarge.jpg", "xlargewidth": "600", "xlargeheight": "400"}, "subtype": "xlarge", "width": 600, "type": "image"}, {"height": 75, "url": "images/2011/11/30/technology/bits-daily-report/bits-daily-report-thumbStandard.jpg", "legacy": {"thumbnail": "images/2011/11/30/technology/bits-daily-report/bits-daily-report-thumbStandard.jpg", "thumbnailwidth": "75", "thumbnailheight": "75"}, "subtype": "thumbnail", "width": 75, "type": "image"}], "pub_date": "2015-05-11T10:23:43Z", "source": "The New York Times", "news_desk": "Business", "keywords": [{"name": "organizations", "value": "Uber Technologies Inc", "rank": "1"}, {"name": "subject", "value": "Start-ups", "rank": "1"}, {"name": "subject", "value": "Venture Capital", "rank": "2"}], "blog": [], "subsection_name": null, "type_of_material": "Blog"}