{"slideshow_credits": null, "snippet": "The documents relate to an investigation and indictment of the man suspected of leading the kidnappers, and provide no evidence that the top leaders of Hamas directed or had prior knowledge of the plot to abduct the three Israeli youths.", "abstract": null, "section_name": "World", "print_page": null, "document_type": "multimedia", "byline": [], "web_url": "http://www.nytimes.com/interactive/2014/09/04/world/middleeast/05israel-doc.html", "lead_paragraph": "The documents relate to an investigation and indictment of the man suspected of leading the kidnappers, and provide no evidence that the top leaders of Hamas directed or had prior knowledge of the plot to abduct the three Israeli youths.", "headline": {"main": "Israel Documents on Hamas Role in Killings of Teenagers"}, "_id": "54091acb38f0d852c36f6abd", "word_count": null, "multimedia": [], "pub_date": "2014-09-04T00:00:00Z", "source": "The New York Times", "news_desk": "World / Middle East", "keywords": [{"name": "subject", "value": "Kidnapping and Hostages", "is_major": "N", "rank": "1"}, {"name": "organizations", "value": "Hamas", "is_major": "N", "rank": "2"}, {"name": "glocations", "value": "Israel", "is_major": "N", "rank": "3"}], "blog": [], "subsection_name": "Middle East", "type_of_material": "Interactive Feature"}