{"slideshow_credits": null, "snippet": "Readers discuss an Op-Ed essay calling capital punishment a &#8220;failed government program.&#8221;", "abstract": "Letter from California Assembly member Tom Ammiano comments on Sept 4 editorial about exoneration of North Carolina men Henry Lee McCollum and Leon Brown.", "section_name": "Opinion", "print_page": "22", "document_type": "article", "byline": [], "web_url": "http://www.nytimes.com/2014/09/15/opinion/the-problems-with-the-death-penalty.html", "lead_paragraph": "Readers discuss an Op-Ed essay calling capital punishment a &#8220;failed government program.&#8221;", "headline": {"main": "The Problems With the Death Penalty", "print_headline": "The Problems With the Death Penalty", "content_kicker": "Letters", "kicker": "Letters"}, "_id": "5416274d38f0d85fde323da8", "word_count": "626", "multimedia": [{"height": 126, "url": "images/2014/09/14/opinion/0915LETTERSwaszul/0915LETTERSwaszul-thumbWide.jpg", "legacy": {"wideheight": "126", "wide": "images/2014/09/14/opinion/0915LETTERSwaszul/0915LETTERSwaszul-thumbWide.jpg", "widewidth": "190"}, "subtype": "wide", "width": 190, "type": "image"}, {"height": 770, "url": "images/2014/09/14/opinion/0915LETTERSwaszul/0915LETTERSwaszul-articleLarge.jpg", "legacy": {"xlarge": "images/2014/09/14/opinion/0915LETTERSwaszul/0915LETTERSwaszul-articleLarge.jpg", "xlargewidth": "600", "xlargeheight": "770"}, "subtype": "xlarge", "width": 600, "type": "image"}, {"height": 75, "url": "images/2014/09/14/opinion/0915LETTERSwaszul/0915LETTERSwaszul-thumbStandard.jpg", "legacy": {"thumbnail": "images/2014/09/14/opinion/0915LETTERSwaszul/0915LETTERSwaszul-thumbStandard.jpg", "thumbnailwidth": "75", "thumbnailheight": "75"}, "subtype": "thumbnail", "width": 75, "type": "image"}], "pub_date": "2014-09-15T00:00:00Z", "source": "The New York Times", "news_desk": "Letters", "keywords": [{"value": "False Arrests, Convictions and Imprisonments", "name": "subject", "is_major": "Y", "rank": "1"}, {"value": "California", "name": "glocations", "is_major": "N", "rank": "11"}, {"value": "United States", "name": "glocations", "is_major": "N", "rank": "12"}, {"value": "United States Politics and Government", "name": "subject", "is_major": "N", "rank": "13"}, {"value": "Editorials", "name": "subject", "is_major": "Y", "rank": "2"}, {"value": "McCollum, Henry Lee", "name": "persons", "is_major": "Y", "rank": "3"}, {"value": "North Carolina", "name": "glocations", "is_major": "Y", "rank": "5"}, {"value": "Murders and Attempted Murders", "name": "subject", "is_major": "Y", "rank": "6"}, {"value": "Capital Punishment", "name": "subject", "is_major": "Y", "rank": "7"}, {"value": "Sentences (Criminal)", "name": "subject", "is_major": "N", "rank": "8"}, {"value": "Conservatism (US Politics)", "name": "subject", "is_major": "N", "rank": "9"}, {"value": "Ammiano, Tom", "name": "persons", "is_major": "N", "rank": "10"}], "blog": [], "subsection_name": null, "type_of_material": "Letter; Editorial"}