{"slideshow_credits": null, "snippet": "The bride works for a philanthropic organization; the groom is in real estate.", "abstract": null, "section_name": "Fashion & Style", "print_page": "23", "document_type": "article", "byline": [], "web_url": "http://www.nytimes.com/2012/12/09/fashion/weddings/alexis-steil-bradley-burwell-weddings.html", "lead_paragraph": "The bride works for a philanthropic organization; the groom is in real estate.", "headline": {"seo": "Alexis Steil, Bradley Burwell &mdash; Weddings", "main": "Alexis Steil and Bradley Burwell", "print_headline": "Alexis Steil, Bradley Burwell"}, "_id": "50c41d7100315214fbb7e704", "word_count": "224", "multimedia": [{"height": 75, "url": "images/2012/12/09/fashion/weddings/09STEILjpg/09STEILjpg-thumbStandard.jpg", "legacy": {"thumbnail": "images/2012/12/09/fashion/weddings/09STEILjpg/09STEILjpg-thumbStandard.jpg", "thumbnailwidth": "75", "thumbnailheight": "75"}, "subtype": "thumbnail", "width": 75, "type": "image"}], "pub_date": "2012-12-09T00:00:00Z", "source": "The New York Times", "news_desk": "Society", "keywords": [{"value": "Weddings and Engagements", "name": "subject", "is_major": "N", "rank": "1"}], "blog": [], "subsection_name": "Weddings/Celebrations", "type_of_material": "News"}