{"slideshow_credits": null, "snippet": "Brian J. Dunn's departure came as the board looked into his \"personal conduct,\" the electronics retailer said.", "abstract": "Brian J. Dunn's departure came as the board looked into his \"personal conduct,\" the electronics retailer said.", "section_name": "Technology", "print_page": null, "document_type": "blogpost", "byline": {"person": [], "original": "By THE NEW YORK TIMES", "organization": "The New York Times"}, "web_url": "http://bits.blogs.nytimes.com/2012/04/11/best-buy-chief-executive-resigns-amid-inquiry/", "lead_paragraph": null, "headline": {"main": "Best Buy Chief Executive Resigns Amid Inquiry", "kicker": "Bits Blog"}, "_id": "4fd3a3c98eb7c8105d8ed876", "word_count": "60", "multimedia": [{"height": 399, "url": "images/2012/04/11/business/Best/Best-articleLarge.jpg", "legacy": {"xlarge": "images/2012/04/11/business/Best/Best-articleLarge.jpg", "xlargewidth": "600", "xlargeheight": "399"}, "subtype": "xlarge", "width": 600, "type": "image"}, {"height": 75, "url": "images/2012/04/11/business/Best/Best-thumbStandard.jpg", "legacy": {"thumbnail": "images/2012/04/11/business/Best/Best-thumbStandard.jpg", "thumbnailwidth": "75", "thumbnailheight": "75"}, "subtype": "thumbnail", "width": 75, "type": "image"}], "pub_date": "2012-04-11T00:57:54Z", "source": "The New York Times", "news_desk": null, "keywords": [], "blog": [], "subsection_name": null, "type_of_material": "Blog"}