{"slideshow_credits": null, "snippet": "Readers respond to a column by Frank Bruni.", "abstract": null, "section_name": "Opinion", "print_page": "22", "document_type": "article", "byline": [], "web_url": "http://www.nytimes.com/2012/04/02/opinion/on-leaving-and-not-leaving-the-church.html", "lead_paragraph": "Readers respond to a column by Frank Bruni.", "headline": {"main": "On Leaving, and Not Leaving, the Church", "print_headline": "On Leaving, and Not Leaving, the Church", "content_kicker": "Letters", "kicker": "Letters"}, "_id": "53f5361f38f0d87ef470e149", "word_count": "886", "multimedia": [], "pub_date": "2012-04-02T00:00:00Z", "source": "The New York Times", "news_desk": "Letters", "keywords": [{"value": "Roman Catholic Church", "name": "organizations", "is_major": "N", "rank": "1"}, {"value": "Colleges and Universities", "name": "subject", "is_major": "N", "rank": "2"}, {"value": "Abortion", "name": "subject", "is_major": "N", "rank": "3"}], "blog": [], "subsection_name": null, "type_of_material": "Letter"}