{"slideshow_credits": null, "snippet": "Highlights from the president-elect\u2019s sit-down interview with reporters, editors and columnists at the New York Times building on Tuesday....", "abstract": null, "section_name": "U.S.", "print_page": null, "document_type": "article", "byline": {"person": [], "original": "By THE NEW YORK TIMES", "organization": "THE NEW YORK TIMES"}, "web_url": "http://www.nytimes.com/2016/11/23/us/politics/your-guide-to-most-important-quotes-times-trump-interview.html", "lead_paragraph": "Highlights from the president-elect\u2019s sit-down interview with reporters, editors and columnists at the New York Times building on Tuesday.", "headline": {"main": "Trump\u2019s Most Important Quotes From His Times Interview, and Why They Matter"}, "_id": "5835e5da7c459f2525d0e0a3", "word_count": "1862", "multimedia": [{"height": 126, "url": "images/2016/11/24/us/24guide1/24guide1-thumbWide.jpg", "legacy": {"wideheight": "126", "wide": "images/2016/11/24/us/24guide1/24guide1-thumbWide.jpg", "widewidth": "190"}, "subtype": "wide", "width": 190, "type": "image"}, {"height": 400, "url": "images/2016/11/24/us/24guide1/24guide1-articleLarge.jpg", "legacy": {"xlarge": "images/2016/11/24/us/24guide1/24guide1-articleLarge.jpg", "xlargewidth": "600", "xlargeheight": "400"}, "subtype": "xlarge", "width": 600, "type": "image"}, {"height": 75, "url": "images/2016/11/24/us/24guide1/24guide1-thumbStandard.jpg", "legacy": {"thumbnail": "images/2016/11/24/us/24guide1/24guide1-thumbStandard.jpg", "thumbnailwidth": "75", "thumbnailheight": "75"}, "subtype": "thumbnail", "width": 75, "type": "image"}], "pub_date": "2016-11-23T18:54:11+0000", "source": "The New York Times", "news_desk": "National", "keywords": [{"name": "persons", "value": "Trump, Donald J", "is_major": "N", "rank": "1"}, {"name": "subject", "value": "United States Politics and Government", "is_major": "N", "rank": "2"}], "blog": [], "subsection_name": "Politics", "type_of_material": "News"}