{"slideshow_credits": null, "snippet": "Shiva Keshavan of India training in Sochi, Russia ahead of the Sochi 2014 Winter Olympics.", "abstract": "Shiva Keshavan of India training in Sochi, Russia ahead of the Sochi 2014 Winter Olympics.", "section_name": "World", "print_page": null, "document_type": "blogpost", "byline": {"person": [], "original": "By THE NEW YORK TIMES", "organization": "The New York Times"}, "web_url": "http://india.blogs.nytimes.com/2014/02/07/image-of-the-day-february-7-2/", "lead_paragraph": null, "headline": {"main": "Image of the Day: February 7", "kicker": "India Ink"}, "_id": "52f5081838f0d81836765836", "word_count": "0", "multimedia": [{"height": 126, "url": "images/2014/02/07/world/asia/07-luge-sochi-IndiaInk/07-luge-sochi-IndiaInk-thumbWide.jpg", "legacy": {"wideheight": "126", "wide": "images/2014/02/07/world/asia/07-luge-sochi-IndiaInk/07-luge-sochi-IndiaInk-thumbWide.jpg", "widewidth": "190"}, "subtype": "wide", "width": 190, "type": "image"}, {"height": 400, "url": "images/2014/02/07/world/asia/07-luge-sochi-IndiaInk/07-luge-sochi-IndiaInk-articleLarge.jpg", "legacy": {"xlarge": "images/2014/02/07/world/asia/07-luge-sochi-IndiaInk/07-luge-sochi-IndiaInk-articleLarge.jpg", "xlargewidth": "600", "xlargeheight": "400"}, "subtype": "xlarge", "width": 600, "type": "image"}, {"height": 75, "url": "images/2014/02/07/world/asia/07-luge-sochi-IndiaInk/07-luge-sochi-IndiaInk-thumbStandard.jpg", "legacy": {"thumbnail": "images/2014/02/07/world/asia/07-luge-sochi-IndiaInk/07-luge-sochi-IndiaInk-thumbStandard.jpg", "thumbnailwidth": "75", "thumbnailheight": "75"}, "subtype": "thumbnail", "width": 75, "type": "image"}], "pub_date": "2014-02-07T11:21:02Z", "source": "The New York Times", "news_desk": null, "keywords": [{"name": "glocations", "value": "Sochi (Russia)", "rank": "3"}, {"name": "glocations", "value": "Russia", "rank": "2"}, {"name": "glocations", "value": "India", "rank": "1"}, {"name": "subject", "value": "Olympic Games (2014)", "rank": "1"}], "blog": [], "subsection_name": "Asia Pacific", "type_of_material": "Blog"}