{"slideshow_credits": null, "snippet": "Describe your interaction with a city or county court, probation system or jail using this form.", "abstract": null, "section_name": "U.S.", "print_page": null, "document_type": "multimedia", "byline": [], "web_url": "http://www.nytimes.com/interactive/2015/us/00debtcriminaljustice.html", "lead_paragraph": "Describe your interaction with a city or county court, probation system or jail using this form.", "headline": {"main": "What Is Your Experience With the Legal System?"}, "_id": "556751c738f0d8572a7b73b4", "word_count": null, "multimedia": [{"height": 126, "url": "images/2015/05/27/us/POLICE-CALLOUT/POLICE-CALLOUT-thumbWide.jpg", "legacy": {"wideheight": "126", "wide": "images/2015/05/27/us/POLICE-CALLOUT/POLICE-CALLOUT-thumbWide.jpg", "widewidth": "190"}, "subtype": "wide", "width": 190, "type": "image"}, {"height": 400, "url": "images/2015/05/27/us/POLICE-CALLOUT/POLICE-CALLOUT-articleLarge.jpg", "legacy": {"xlarge": "images/2015/05/27/us/POLICE-CALLOUT/POLICE-CALLOUT-articleLarge.jpg", "xlargewidth": "600", "xlargeheight": "400"}, "subtype": "xlarge", "width": 600, "type": "image"}, {"height": 75, "url": "images/2015/05/27/us/POLICE-CALLOUT/POLICE-CALLOUT-thumbStandard.jpg", "legacy": {"thumbnail": "images/2015/05/27/us/POLICE-CALLOUT/POLICE-CALLOUT-thumbStandard.jpg", "thumbnailwidth": "75", "thumbnailheight": "75"}, "subtype": "thumbnail", "width": 75, "type": "image"}], "pub_date": "2015-07-20T13:44:55Z", "source": "The New York Times", "news_desk": "U.S.", "keywords": [{"name": "subject", "value": "Prisons and Prisoners", "is_major": "N", "rank": "1"}, {"name": "subject", "value": "Crime and Criminals", "is_major": "N", "rank": "2"}], "blog": [], "subsection_name": null, "type_of_material": "Interactive Feature"}