{"slideshow_credits": null, "snippet": "Serena Williams became the eighth woman in the Open era to reach 700 career victories, beating Sabine Lisicki, 7-6 (4), 1-6, 6-3.", "abstract": "Serena Williams defeats Sabine Lisicki to reach semifinals at Miami Open tennis tournament.", "section_name": "Sports", "print_page": "14", "document_type": "article", "byline": {"person": [], "organization": "THE ASSOCIATED PRESS", "original": "By THE ASSOCIATED PRESS", "contributor": ""}, "web_url": "http://www.nytimes.com/2015/04/02/sports/tennis/serena-williams-earns-700th-victory.html", "lead_paragraph": "Serena Williams became the eighth woman in the Open era to reach 700 career victories, beating Sabine Lisicki, 7-6 (4), 1-6, 6-3.", "headline": {"main": "Serena Williams Earns 700th Victory", "content_kicker": "Sports Briefing | Tennis", "print_headline": "Serena Williams Earns 700th Victory"}, "_id": "551cba9238f0d87335c1a33e", "word_count": "53", "multimedia": [], "pub_date": "2015-04-02T00:00:00Z", "source": "The New York Times", "news_desk": "Sports", "keywords": [{"name": "subject", "value": "Tennis", "is_major": "Y", "rank": "1"}, {"name": "persons", "value": "Williams, Serena", "is_major": "N", "rank": "2"}, {"name": "persons", "value": "Lisicki, Sabine", "is_major": "N", "rank": "3"}], "blog": [], "subsection_name": "Tennis", "type_of_material": "Brief"}