{"snippet": "The outward train for Worcester, this morning at the crossing of the Providence track, came in collision with the train from Dedham, the engine striking the second car broadside and smashing it to atoms. The car was fortunately empty and no person...", "document_type": "article", "word_count": 179, "multimedia": [], "byline": null, "web_url": "http://query.nytimes.com/gst/abstract.html?res=9400E4DD1431E13BBC4153DFB667838A649FDE", "pub_date": "1851-10-09T00:03:58Z", "type_of_material": "Article", "section_name": null, "lead_paragraph": "The outward train for Worcester, this morning at the crossing of the Providence track, came in collision with the train from Dedham, the engine striking the second car broadside and smashing it to atoms. The car was fortunately empty and no person was hurt. The engine and tender of the Worcester train were thrown off the track.", "source": "The New York Times", "headline": {"kicker": "1", "main": "Railroad Accident--The New-Hampshire State Fair."}, "blog": [], "subsection_name": null, "slideshow_credits": null, "news_desk": null, "keywords": [], "_id": "4fbfd25545c1498b0d005414", "abstract": null, "print_page": "2"}