{"snippet": "By the arrival yesterday of the schooner G. B. Mathew, from Belize, Honduras, we have received files of The Honduras Watchman to the 6th ult. We learn from these papers that the determination of the English Government to take possession of Ruatan ...", "document_type": "article", "word_count": 439, "multimedia": [], "byline": null, "web_url": "http://query.nytimes.com/gst/abstract.html?res=9D00E5DC1331E234BC4852DFB667838A649FDE", "pub_date": "1851-10-10T00:03:58Z", "type_of_material": "Article", "section_name": null, "lead_paragraph": "By the arrival yesterday of the schooner G. B. Mathew, from Belize, Honduras, we have received files of The Honduras Watchman to the 6th ult. We learn from these papers that the determination of the English Government to take possession of Ruatan and other islands along the coast, is no longer concealed. A meeting of the British residents of Ruatan has been held, at which a plan of government for the island was drawn up.", "source": "The New York Times", "headline": {"main": "Later from Honduras."}, "blog": [], "subsection_name": null, "slideshow_credits": null, "news_desk": null, "keywords": [{"value": "HONDURAS", "name": "glocations"}], "_id": "4fbfd25545c1498b0d005580", "abstract": "Declaration of the Ruatan Islanders", "print_page": "4"}