{"slideshow_credits": "Liz Barclay for The New York Times", "snippet": "Angie Mar, the chef and owner, has transformed this West Village restaurant into a meat lover\u2019s palace like no other....", "abstract": null, "section_name": "Food", "print_page": null, "document_type": "multimedia", "byline": [], "web_url": "http://www.nytimes.com/slideshow/2016/10/26/dining/the-beatrice-inn.html", "lead_paragraph": "Angie Mar, the chef and owner, has transformed this West Village restaurant into a meat lover\u2019s palace like no other.", "headline": {"main": "The Beatrice Inn"}, "_id": "580f78db95d0e022439c51a7", "word_count": "20", "multimedia": [{"height": 126, "url": "images/2016/10/26/dining/26REST-BEATRICE-INN-slide-DW9V/26REST-BEATRICE-INN-slide-DW9V-thumbWide.jpg", "legacy": {"wideheight": "126", "wide": "images/2016/10/26/dining/26REST-BEATRICE-INN-slide-DW9V/26REST-BEATRICE-INN-slide-DW9V-thumbWide.jpg", "widewidth": "190"}, "subtype": "wide", "width": 190, "type": "image"}, {"height": 401, "url": "images/2016/10/26/dining/26REST-BEATRICE-INN-slide-DW9V/26REST-BEATRICE-INN-slide-DW9V-articleLarge.jpg", "legacy": {"xlarge": "images/2016/10/26/dining/26REST-BEATRICE-INN-slide-DW9V/26REST-BEATRICE-INN-slide-DW9V-articleLarge.jpg", "xlargewidth": "600", "xlargeheight": "401"}, "subtype": "xlarge", "width": 600, "type": "image"}, {"height": 75, "url": "images/2016/10/26/dining/26REST-BEATRICE-INN-slide-DW9V/26REST-BEATRICE-INN-slide-DW9V-thumbStandard.jpg", "legacy": {"thumbnail": "images/2016/10/26/dining/26REST-BEATRICE-INN-slide-DW9V/26REST-BEATRICE-INN-slide-DW9V-thumbStandard.jpg", "thumbnailwidth": "75", "thumbnailheight": "75"}, "subtype": "thumbnail", "width": 75, "type": "image"}], "pub_date": "2016-10-25T15:22:58+0000", "source": "The New York Times", "news_desk": "Food", "keywords": [{"name": "subject", "value": "Restaurants", "is_major": "N", "rank": "1"}, {"name": "glocations", "value": "West Village (Manhattan, NY)", "is_major": "N", "rank": "2"}, {"name": "organizations", "value": "Beatrice Inn (Manhattan, NY, Restaurant)", "is_major": "N", "rank": "3"}, {"name": "persons", "value": "Mar, Angela (Chef)", "is_major": "N", "rank": "4"}], "blog": [], "subsection_name": null, "type_of_material": "Slideshow"}