{"slideshow_credits": null, "snippet": "Recent legislation in Russia has spurred an international furor and a national debate on gays in society.", "abstract": null, "section_name": "World", "print_page": "", "document_type": "article", "byline": {"person": [], "organization": "THE NEW YORK TIMES", "original": "By THE NEW YORK TIMES", "contributor": ""}, "web_url": "http://www.nytimes.com/2013/08/12/world/europe/tell-us-about-your-experiences-being-gay-in-russia.html", "lead_paragraph": "Recent legislation in Russia has spurred an international furor and a national debate on gays in society.", "headline": {"main": "Tell Us About Your Experiences Being Gay in Russia / \u0411\u044b\u0442\u044c \u0433\u0435\u0435\u043c \u0432 \u0420\u043e\u0441\u0441\u0438\u0438: \u0440\u0430\u0441\u0441\u043a\u0430\u0436\u0438\u0442\u0435 \u043e \u0432\u0430\u0448\u0435\u043c \u043b\u0438\u0447\u043d\u043e\u043c \u043e\u043f\u044b\u0442\u0435"}, "_id": "52085af738f0d8740ac8afb8", "word_count": "235", "multimedia": [], "pub_date": "2013-08-12T00:00:00Z", "source": "The New York Times", "news_desk": "Foreign", "keywords": [{"value": "Russia", "name": "glocations", "is_major": "N", "rank": "1"}, {"value": "Homosexuality", "name": "subject", "is_major": "N", "rank": "3"}, {"value": "Law and Legislation", "name": "subject", "is_major": "N", "rank": "2"}], "blog": [], "subsection_name": "Europe", "type_of_material": "News"}