{"slideshow_credits": null, "snippet": "Readers seek to ensure that the next president is not \u201cleveraging the country\u2019s business for the benefit of his own.\u201d...", "abstract": null, "section_name": "Opinion", "print_page": "18", "document_type": "article", "byline": [], "web_url": "http://www.nytimes.com/2016/12/23/opinion/taking-action-to-address-trump-conflicts.html", "lead_paragraph": "Readers seek to ensure that the next president is not \u201cleveraging the country\u2019s business for the benefit of his own.\u201d", "headline": {"print_headline": "Taking Action to Address Conflicts of Interest", "main": "Taking Action to Address Trump Conflicts", "content_kicker": "Letters", "kicker": "Letters"}, "_id": "585d67eb95d0e03926077991", "word_count": "421", "multimedia": [], "pub_date": "2016-12-23T18:07:33+0000", "source": "The New York Times", "news_desk": "Letters", "keywords": [{"name": "subject", "value": "Conflicts of Interest", "is_major": "N", "rank": "1"}, {"name": "persons", "value": "Trump, Donald J", "is_major": "N", "rank": "2"}], "blog": [], "subsection_name": null, "type_of_material": "Letter"}