{"slideshow_credits": null, "snippet": "In 2008, Barack Obama became the first Democrat to win Virginia in more than 40 years, in part because of inroads he made in the Richmond area and growing suburbs in the southern part of the state.", "abstract": null, "section_name": "U.S.", "print_page": null, "document_type": "multimedia", "byline": null, "web_url": "http://www.nytimes.com/interactive/2012/05/05/us/politics/turning-virginia-blue.html", "lead_paragraph": "In 2008, Barack Obama became the first Democrat to win Virginia in more than 40 years, in part because of inroads he made in the Richmond area and growing suburbs in the southern part of the state.", "headline": {"seo": "Turning Virginia Blue", "main": "Turning Virginia Blue"}, "_id": "53f66ffe38f0d821a37b21d0", "word_count": "31", "multimedia": [], "pub_date": "2012-05-05T00:00:00Z", "source": "The New York Times", "news_desk": "U.S. / Politics", "keywords": [{"value": "Virginia", "name": "glocations", "is_major": "N", "rank": "1"}, {"value": "Obama, Barack", "name": "persons", "is_major": "N", "rank": "2"}, {"value": "Presidential Election of 2008", "name": "subject", "is_major": "N", "rank": "3"}, {"value": "Presidential Election of 2012", "name": "subject", "is_major": "N", "rank": "4"}], "blog": [], "subsection_name": "Politics", "type_of_material": "Interactive Feature"}