{"slideshow_credits": null, "snippet": "Because of Columbus Day, alternate-side street-cleaning regulations will be suspended.", "abstract": null, "section_name": "N.Y. / Region", "print_page": "17", "document_type": "article", "byline": [], "web_url": "http://www.nytimes.com/2015/10/12/nyregion/12parkingbox.html", "lead_paragraph": "Because of Columbus Day, alternate-side street-cleaning regulations will be suspended.", "headline": {"main": "New York Parking Alert: Alternate-Side Parking Rules Suspended on Monday", "print_headline": "Parking Rules"}, "_id": "561b040738f0d839bd910fd5", "word_count": "22", "multimedia": [], "pub_date": "2015-10-12T00:00:00Z", "source": "The New York Times", "news_desk": "Metro", "keywords": [{"name": "subject", "value": "Parking", "is_major": "N", "rank": "1"}, {"name": "subject", "value": "Columbus Day", "is_major": "N", "rank": "2"}, {"name": "glocations", "value": "New York City", "is_major": "N", "rank": "3"}], "blog": [], "subsection_name": null, "type_of_material": "News"}