{"slideshow_credits": null, "snippet": "The father of two Syrian boys, who drowned with their mother as they were trying to reach Greece, spoke before they were laid to rest in the Syrian town of Kobani.", "abstract": null, "section_name": "World", "print_page": null, "document_type": "multimedia", "byline": {"person": [], "original": "By REUTERS", "organization": "REUTERS"}, "web_url": "http://www.nytimes.com/video/world/middleeast/100000003891643/funeral-held-for-galip-and-aylan-kurdi.html", "lead_paragraph": "The father of two Syrian boys, who drowned with their mother as they were trying to reach Greece, spoke before they were laid to rest in the Syrian town of Kobani.", "headline": {"main": "Funeral Held for Galip and Aylan Kurdi"}, "_id": "55e9b3a138f0d82b9387d821", "word_count": "31", "multimedia": [{"height": 126, "url": "images/2015/09/05/world/05migrant1_hp/05migrant1_hp-thumbWide.jpg", "legacy": {"wideheight": "126", "wide": "images/2015/09/05/world/05migrant1_hp/05migrant1_hp-thumbWide.jpg", "widewidth": "190"}, "subtype": "wide", "width": 190, "type": "image"}, {"height": 358, "url": "images/2015/09/05/world/05migrant1_hp/05migrant1_hp-articleLarge.jpg", "legacy": {"xlarge": "images/2015/09/05/world/05migrant1_hp/05migrant1_hp-articleLarge.jpg", "xlargewidth": "600", "xlargeheight": "358"}, "subtype": "xlarge", "width": 600, "type": "image"}, {"height": 75, "url": "images/2015/09/05/world/05migrant1_hp/05migrant1_hp-thumbStandard.jpg", "legacy": {"thumbnail": "images/2015/09/05/world/05migrant1_hp/05migrant1_hp-thumbStandard.jpg", "thumbnailwidth": "75", "thumbnailheight": "75"}, "subtype": "thumbnail", "width": 75, "type": "image"}], "pub_date": "2015-09-04T11:06:38Z", "source": "The New York Times", "news_desk": "World / Middle East", "keywords": [{"name": "subject", "value": "Middle East and Africa Migrant Crisis", "is_major": "N", "rank": "1"}, {"name": "subject", "value": "Maritime Accidents and Safety", "is_major": "N", "rank": "11"}, {"name": "persons", "value": "Kurdi, Aylan (2011-15)", "is_major": "N", "rank": "2"}, {"name": "persons", "value": "Kurdi, Galip (d 2015)", "is_major": "N", "rank": "3"}, {"name": "subject", "value": "Funerals and Memorials", "is_major": "N", "rank": "4"}, {"name": "glocations", "value": "Kobani (Syria)", "is_major": "N", "rank": "5"}, {"name": "glocations", "value": "Syria", "is_major": "N", "rank": "6"}, {"name": "subject", "value": "Drownings", "is_major": "N", "rank": "7"}, {"name": "glocations", "value": "Europe", "is_major": "N", "rank": "8"}, {"name": "glocations", "value": "Greece", "is_major": "N", "rank": "9"}, {"name": "glocations", "value": "Turkey", "is_major": "N", "rank": "10"}], "blog": [], "subsection_name": "Middle East", "type_of_material": "Video"}