{"slideshow_credits": null, "snippet": "The United States needed overtime to beat Kazakhstan, 4-3, at the world championship in Belarus.", "abstract": "United States hockey team beats Kazakhstan, 4-3, at world championships in Belarus.", "section_name": "Sports", "print_page": "7", "document_type": "article", "byline": {"person": [], "organization": "THE ASSOCIATED PRESS", "original": "By THE ASSOCIATED PRESS", "contributor": ""}, "web_url": "http://www.nytimes.com/2014/05/17/sports/us-edges-kazakhstan.html", "lead_paragraph": "The United States needed overtime to beat Kazakhstan, 4-3, at the world championship in Belarus.", "headline": {"main": "U.S. Edges Kazakhstan", "print_headline": "U.S. Edges Kazakhstan", "content_kicker": "Sports Briefing | Hockey"}, "_id": "5376f08c38f0d821cdd01886", "word_count": "51", "multimedia": [], "pub_date": "2014-05-17T00:00:00Z", "source": "The New York Times", "news_desk": "Sports", "keywords": [{"value": "Jones, Seth (1994- )", "name": "persons", "is_major": "N", "rank": "2"}, {"value": "Hockey, Ice", "name": "subject", "is_major": "Y", "rank": "1"}, {"value": "Belarus", "name": "glocations", "is_major": "N", "rank": "3"}], "blog": [], "subsection_name": null, "type_of_material": "Brief"}