{"slideshow_credits": null, "snippet": "Senators have proposed an immigration bill that could give a legal second chance to tens of thousands of deportees.", "abstract": null, "section_name": "U.S.", "print_page": null, "document_type": "multimedia", "byline": [], "web_url": "http://www.nytimes.com/slideshow/2013/05/08/us/politics/20130509_DEPORTEE.html", "lead_paragraph": "Senators have proposed an immigration bill that could give a legal second chance to tens of thousands of deportees.", "headline": {"main": "A Chance to Return"}, "_id": "518ae386cf28d05efe001a5b", "word_count": "19", "multimedia": [{"height": 126, "url": "images/2013/05/08/us/20130509_DEPORTEE-slide-W0OJ/20130509_DEPORTEE-slide-W0OJ-thumbWide.jpg", "legacy": {"wideheight": "126", "wide": "images/2013/05/08/us/20130509_DEPORTEE-slide-W0OJ/20130509_DEPORTEE-slide-W0OJ-thumbWide.jpg", "widewidth": "190"}, "subtype": "wide", "width": 190, "type": "image"}, {"height": 400, "url": "images/2013/05/08/us/20130509_DEPORTEE-slide-W0OJ/20130509_DEPORTEE-slide-W0OJ-articleLarge.jpg", "legacy": {"xlarge": "images/2013/05/08/us/20130509_DEPORTEE-slide-W0OJ/20130509_DEPORTEE-slide-W0OJ-articleLarge.jpg", "xlargewidth": "600", "xlargeheight": "400"}, "subtype": "xlarge", "width": 600, "type": "image"}, {"height": 75, "url": "images/2013/05/08/us/20130509_DEPORTEE-slide-W0OJ/20130509_DEPORTEE-slide-W0OJ-thumbStandard.jpg", "legacy": {"thumbnail": "images/2013/05/08/us/20130509_DEPORTEE-slide-W0OJ/20130509_DEPORTEE-slide-W0OJ-thumbStandard.jpg", "thumbnailwidth": "75", "thumbnailheight": "75"}, "subtype": "thumbnail", "width": 75, "type": "image"}], "pub_date": "2013-05-08T00:00:00Z", "source": "The New York Times", "news_desk": "U.S. / Politics", "keywords": [{"name": "subject", "value": "Illegal Immigration", "is_major": "N", "rank": "1"}, {"name": "subject", "value": "Deportation", "is_major": "N", "rank": "2"}, {"name": "glocations", "value": "Mexico", "is_major": "N", "rank": "3"}], "blog": [], "subsection_name": "Politics", "type_of_material": "Slideshow"}