{"slideshow_credits": null, "snippet": "Video of Edward J. Snowden with international rights activists in Moscow on Friday was posted on the Russian news site Life News.", "abstract": null, "section_name": "World", "print_page": null, "document_type": "multimedia", "byline": [], "web_url": "http://www.nytimes.com/video/world/europe/100000002333678/snowden-on-video-with-activists.html", "lead_paragraph": "Video of Edward J. Snowden with international rights activists in Moscow on Friday was posted on the Russian news site Life News.", "headline": {"main": "Snowden Makes Appeal From Airport"}, "_id": "51e03e2a7e0d9c0839d2f740", "word_count": "22", "multimedia": [{"height": 126, "url": "images/2013/07/13/world/13snowden2_337-copy/13snowden2_337-copy-thumbWide-v2.jpg", "legacy": {"wideheight": "126", "wide": "images/2013/07/13/world/13snowden2_337-copy/13snowden2_337-copy-thumbWide-v2.jpg", "widewidth": "190"}, "subtype": "wide", "width": 190, "type": "image"}, {"height": 337, "url": "images/2013/07/13/world/13snowden2_337-copy/13snowden2_337-copy-articleLarge-v2.jpg", "legacy": {"xlarge": "images/2013/07/13/world/13snowden2_337-copy/13snowden2_337-copy-articleLarge-v2.jpg", "xlargewidth": "600", "xlargeheight": "337"}, "subtype": "xlarge", "width": 600, "type": "image"}, {"height": 75, "url": "images/2013/07/13/world/13snowden2_337-copy/13snowden2_337-thumbStandard.jpg", "legacy": {"thumbnail": "images/2013/07/13/world/13snowden2_337-copy/13snowden2_337-thumbStandard.jpg", "thumbnailwidth": "75", "thumbnailheight": "75"}, "subtype": "thumbnail", "width": 75, "type": "image"}], "pub_date": "2013-07-12T13:34:26Z", "source": "The New York Times", "news_desk": "World / Europe", "keywords": [{"name": "persons", "value": "Snowden, Edward J", "is_major": "N", "rank": "1"}, {"name": "glocations", "value": "Russia", "is_major": "N", "rank": "2"}, {"name": "organizations", "value": "Human Rights Watch", "is_major": "N", "rank": "3"}, {"name": "subject", "value": "Surveillance of Citizens by Government", "is_major": "N", "rank": "4"}, {"name": "organizations", "value": "National Security Agency", "is_major": "N", "rank": "5"}, {"name": "subject", "value": "Classified Information and State Secrets", "is_major": "N", "rank": "6"}], "blog": [], "subsection_name": "Europe", "type_of_material": "Video"}