{"slideshow_credits": null, "snippet": "The acquittal of George Zimmerman should be a call to reform laws that make it easier to kill.", "abstract": "Editorial contends case of George Zimmerman, who was acquitted of all charges in killing of Trayvon Martin, is a sad commentary on the state of race relations and battle over gun rights in America today.", "section_name": "Opinion", "print_page": "16", "document_type": "article", "byline": {"person": [], "organization": "THE EDITORIAL BOARD", "original": "By THE EDITORIAL BOARD", "contributor": ""}, "web_url": "http://www.nytimes.com/2013/07/15/opinion/trayvon-martins-legacy.html", "lead_paragraph": "The acquittal of George Zimmerman should be a call to reform laws that make it easier to kill.", "headline": {"main": "Trayvon Martin\u2019s Legacy", "print_headline": "Trayvon Martin\u2019s Legacy", "content_kicker": "Editorial", "kicker": "Editorial"}, "_id": "51e34d3d7e0d9c0839d2fbb7", "word_count": "441", "multimedia": [], "pub_date": "2013-07-15T00:00:00Z", "source": "The New York Times", "news_desk": "Editorial", "keywords": [{"value": "Zimmerman, George", "name": "persons", "is_major": "Y", "rank": "1"}, {"value": "Martin, Trayvon", "name": "persons", "is_major": "Y", "rank": "2"}, {"value": "Gun Control", "name": "subject", "is_major": "Y", "rank": "3"}, {"value": "Race and Ethnicity", "name": "subject", "is_major": "N", "rank": "4"}, {"value": "Discrimination", "name": "subject", "is_major": "N", "rank": "5"}, {"value": "Editorials", "name": "subject", "is_major": "Y", "rank": "6"}, {"value": "Blacks", "name": "subject", "is_major": "Y", "rank": "7"}], "blog": [], "subsection_name": null, "type_of_material": "Editorial"}